tee_no_clobber/__init__.py
tee_no_clobber/main.py
tee_no_clobber-1.0.0.dist-info/METADATA
tee_no_clobber-1.0.0.dist-info/WHEEL
tee_no_clobber-1.0.0.dist-info/entry_points.txt
tee_no_clobber-1.0.0.dist-info/top_level.txt
tee_no_clobber-1.0.0.dist-info/RECORD
